heavyedge_landmarks/__init__.py
heavyedge_landmarks/mathematical.py
heavyedge_landmarks/plateau.py
heavyedge_landmarks/preshape.py
heavyedge_landmarks/pseudo.py
heavyedge_landmarks/scale.py
heavyedge_landmarks-1.5.0.dist-info/licenses/LICENSE
heavyedge_landmarks-1.5.0.dist-info/METADATA
heavyedge_landmarks-1.5.0.dist-info/WHEEL
heavyedge_landmarks-1.5.0.dist-info/top_level.txt
heavyedge_landmarks-1.5.0.dist-info/RECORD
